usefuladbwithrestart/README.MD
usefuladbwithrestart/__init__.py
usefuladbwithrestart/requirements.txt
usefuladbwithrestart/thirdparty.json
usefuladbwithrestart-0.10.dist-info/LICENSE.rst
usefuladbwithrestart-0.10.dist-info/METADATA
usefuladbwithrestart-0.10.dist-info/WHEEL
usefuladbwithrestart-0.10.dist-info/top_level.txt
usefuladbwithrestart-0.10.dist-info/RECORD
